vulntext/__init__.py
vulntext/main.py
vulntext/prompts.py
vulntext-2025.12.21084032.dist-info/METADATA
vulntext-2025.12.21084032.dist-info/WHEEL
vulntext-2025.12.21084032.dist-info/top_level.txt
vulntext-2025.12.21084032.dist-info/RECORD
