Metadata-Version: 2.4
Name: vulntext
Version: 2025.12.21084032
Summary: A new package that analyzes user-provided text to extract structured information about software security vulnerabilities. It processes natural language descriptions of code issues or security concerns
Author-email: vulntext <hi@eugene.plus>
License: MIT
Project-URL: Homepage, https://github.com/chigwell/vulntext
Requires-Python: >=3.9
Requires-Dist: langchain-llm7>=0.0.0
Requires-Dist: llmatch-messages>=0.0.0
Requires-Dist: langchain-core>=0.3.0
